fastapi_tailwind/__init__.py
fastapi_tailwind/binary.py
fastapi_tailwind/errors.py
fastapi_tailwind/tailwind.py
fastapi_tailwind/binary/metadata.txt
fastapi_tailwind/binary/tailwindcss-macos-arm64
fastapi_tailwind-2.0.4a1.dist-info/licenses/LICENSE
fastapi_tailwind-2.0.4a1.dist-info/METADATA
fastapi_tailwind-2.0.4a1.dist-info/WHEEL
fastapi_tailwind-2.0.4a1.dist-info/top_level.txt
fastapi_tailwind-2.0.4a1.dist-info/RECORD
