Metadata-Version: 2.4
Name: fastapi-tailwind
Version: 2.0.4a1
Summary: ✨ TailwindCSS support for 🔥 FastAPI.
Author-email: Goldy <goldy@devgoldy.xyz>
License: MIT License
Project-URL: GitHub, https://github.com/THEGOLDENPRO/fastapi-tailwind
Project-URL: BugTracker, https://github.com/THEGOLDENPRO/fastapi-tailwind/issues
Keywords: tailwindcss,tailwind,fastapi,fastapi middleware,tailwindcss v4
Classifier: Operating System :: Microsoft :: Windows :: Windows 11
Classifier: Operating System :: Microsoft :: Windows :: Windows 10
Classifier: Operating System :: POSIX :: Linux
Classifier: Operating System :: MacOS
Classifier: License :: OSI Approved :: MIT License
Classifier: Programming Language :: Python :: 3.9
Classifier: Programming Language :: Python :: 3.10
Classifier: Programming Language :: Python :: 3.11
Classifier: Programming Language :: Python :: 3.12
Classifier: Programming Language :: Python :: 3.13
Requires-Python: >=3.8
License-File: LICENSE
Provides-Extra: dev
Requires-Dist: ruff; extra == "dev"
Requires-Dist: build; extra == "dev"
Requires-Dist: fastapi[standard]; extra == "dev"
Requires-Dist: requests; extra == "dev"
Requires-Dist: typer; extra == "dev"
Requires-Dist: pytest; extra == "dev"
Dynamic: license-file
